gownak.sv
module gownak (
    clk,
    PC,
    instruction,

    //ALU
    i_a,
    i_b,
    operation,
    i_result,
    over,



    reg_0,
    reg_1,
    reg_2,
    reg_3,
    reg_4,
    reg_5

);
    input   reg clk;                //тактовый сигнал
    output  reg [31:0]  PC;             // Program Counter
    output  reg [31:0]  instruction;    
    reg [31:0] FLAG;    // флаговый регистр 

    // инициализация регистров
    initial 
    begin
        PC =            32'h00000000;
        FLAG =          32'h00000000;
    end
    

    // тут 32бит x 32шт регистра общего назначения
    output reg [31:0] registers[0:31];
    initial 
    begin
        registers[0] = 1;
        for (integer i = 0; i < 32; i = i + 1) 
        begin
            registers[i] <= 32'b0;
        end
    end
    output  reg [31:0]  reg_0,reg_1,reg_2,reg_3,reg_4,reg_5;
    assign reg_0 = registers[0];
    assign reg_1 = registers[1];
    assign reg_2 = registers[2];
    assign reg_3 = registers[3];
    assign reg_4 = registers[4];
    assign reg_5 = registers[5];


    // тактовый блок
    always @(posedge clk) 
    begin
        PC <= PC + 1;
    end

   
    instruction_memory instruction_memory_gate (
      .address(PC),
      .instruction(instruction)     
    );


    ///////////////////////////////////
    output reg [4:0]    i_a;
    output reg [4:0]    i_b;
    output reg [5:0]    operation;
    output reg [4:0]    i_result;
    output reg [31:0]   over;

    assign operation = instruction[32:26];
    assign i_result  = instruction[14:10];
    assign i_a       = instruction[9:5];
    assign i_b       = instruction[4:0];


    // инструкция записи в регистр
    always @(negedge clk) 
    begin
        if (operation == 6'b010000)
        begin
            registers[i_result] <= instruction[9:0];
        end
    end

    // ALU
    always @(negedge clk) begin
        // выбираем операцию на основе входного кода операции
        case (operation)  
            6'b000001: registers[i_result] <= registers[i_a] + registers[i_b];      // сложение
            6'b000010: registers[i_result] <= registers[i_a] - registers[i_b];      // вычитание
            6'b000011: registers[i_result] <= registers[i_a] * registers[i_b];      // умножение
            6'b000100: registers[i_result] <= registers[i_a] / registers[i_b];      // деление
            6'b000101: registers[i_result] <= registers[i_a] & registers[i_b];      // AND
            6'b000110: registers[i_result] <= registers[i_a] | registers[i_b];      // OR
            6'b000111: registers[i_result] <= registers[i_a] ^ registers[i_b];      // XOR
            6'b001000: registers[i_result] <= ~(registers[i_a] | registers[i_b]);   // NOR result = ~(a | b);
            6'b001001: registers[i_result] <= registers[i_a] << i_b;     // сдвиг влево result = a << b;
            6'b001010: registers[i_result] <= registers[i_a] >> i_b;     // арифметический сдвиг вправо result = a >> b;
            6'b001011: registers[i_result] <= registers[i_a] >>> i_b;     // логический сдвиг вправо       // сложение result = a >>> b;

            6'b100000: PC <= (PC ^ PC) + instruction[25:0] - 1;                 //приыжок без условия 
            //6'b100001: begin if (registers[0] == 0) begin PC <= (PC ^ PC) + instruction[20:0] - 1 end end;                 //приыжок если выбранный регистр равен 0
          //6'b100001:  PC <= ((registers[0] == 32'b0)&(instruction[15:0]-1)) | ((registers[0] != 32'b0)&PC);                 //приыжок если выбранный регистр равен 0
            6'b100001:  PC <= (registers[0] == 32'b0) ? (instruction[15:0]-1) : PC;
            //ФОРМАТ           iiiiiiRRRRRadresadresadresadresa
            //memory[15]   = 32'b10001000000000000000000000000111;   // прыжок если регистр равен 0

            6'b100010:  PC <= (registers[i_a] > registers[i_b]) ? (instruction[26:10]-1) : PC;

        endcase
    end


    //alu alu_gate (
    //  .address(PC),
    //  .instruction(instruction)     
    //);

    //input [31:0] a,             // первый операнд
    //input [31:0] b,             // второй операнд
    //input [5:0]  operation,     // код операции
    //output reg [31:0] result,    // результат
    //output reg [31:0] over // для остатока или переполнение

    
    
endmodule


module instruction_memory 
(
    address,      // адрес инструкции
    instruction   // адрес инструкции
);

    input   wire [31:0] address;        // адрес инструкции
    output  reg  [31:0] instruction;    // адрес инструкциии

    // 256 x 32-битная память
    reg [31:0] memory [0:255]; 
    initial 
    begin

        memory[0]   = 32'b00000000000000000000000000000000;   // NOP
        //ФОРМАТ          iiiiii           RRRRRaaaaaaaaaa
        memory[1]   = 32'b01000000000000000000010000011110;   // запись A = 30 в регистр 1
        //ФОРМАТ          iiiiii           RRRRRaaaaaaaaaa
        memory[2]   = 32'b01000000000000000000100000010010;   // запись B = 18 в регистр 2

        memory[3]   = 32'b00000000000000000000000000000000;   // NOP

        //                iiiiii           RRRRRaaaaabbbbb
        memory[4]   = 32'b00001000000000000000000000100010;   // REG_0 = A - B

        memory[5]   = 32'b10000100000000000000000010000000;   // прыжок если REG_0 равен 0


        //ФОРМАТ          iiiiii                aaaaabbbbb
        memory[6]   = 32'b10001000000000000010010000100010;   // прыжок если A > B
        //                iiiiii           RRRRRaaaaabbbbb
        memory[7]   = 32'b00001000000000000000100001000001;   // B = B - A

        //ФОРМАТ           iiiiiiAGRESAGRESAGRESAGRESAGRESA           
        memory[8]   = 32'b10000000000000000000000000000011;   // прыжок без условия

        //                iiiiii           RRRRRaaaaabbbbb
        memory[9]   = 32'b00001000000000000000010000100010;   // A = A - B

        //ФОРМАТ           iiiiiiAGRESAGRESAGRESAGRESAGRESA           
        memory[10]   = 32'b10000000000000000000000000000011;   // прыжок без условия



        //ФОРМАТ          iiiiii           RRRRRaaaaabbbbb
        //memory[3]   = 32'b00001000000000000000000000100010;    // вычетание  REG_0 = A - B
        //ФОРМАТ           iiiiiiRRRRRadresadresadresadresa
        //memory[4]   = 32'b1000010000000000000000010000000;   // прыжок в конец если REG_0 равен 0






        /*
        // инструкции в памяти тут, 
        // формат = 32'hXXXXXXXX;
        // i - инструкция R - результат а - 1 операнд b - второй операнд 
        //ФОРМАТ          iiiiii           RRRRRaaaaabbbbb      
        memory[0]   = 32'b00000000000000000000000000000000;   // NOP
        // проверка ALU
        memory[1]   = 32'b01000000000000000000000001100000;   // запись
        memory[2]   = 32'b01000000000000000000010000100000;   // запись
        memory[3]   = 32'b00000100000000000000100000000001;   // сложение
        memory[4]   = 32'b00001000000000000000100000000001;   // вычетание 
        memory[5]   = 32'b00001100000000000000100000000001;   // умножение
        memory[6]   = 32'b00010000000000000000100000000001;   // деление
        memory[7]   = 32'b00010100000000000000100000000001;   // AND
        memory[8]   = 32'b00011000000000000000100000000001;   // OR
        memory[9]   = 32'b00011100000000000000100000000001;   // XOR
        memory[10]  = 32'b00100000000000000000100000000001;   // NOR
        memory[11]  = 32'b00100100000000000000100000000001;   // сдвиг влево result = a << b;
        memory[12]  = 32'b00101000000000000000100000000001;   // арифметический сдвиг вправо result = a >> b;
        memory[13]  = 32'b00101100000000000000100000000001;   // логический сдвиг вправо       // сложение result = a >>> b;

        // проверка JMP
        //ФОРМАТ          iiiiiiAGRESAGRESAGRESAGRESAGRESAG            
        //memory[14]   = 32'b10000000000000000000000000000010;   // прыжок без условия
        memory[14]   = 32'b00000000000000000000000000000000;     // NOP


        memory[15]   = 32'b00000000000000000000000000000000;   // NOP
        memory[16]   = 32'b00000000000000000000000000000000;   // NOP
        //ФОРМАТ           iiiiiiRRRRRadresadresadresadresa
      //memory[17]   = 32'b10000100000000000000000000000010;   // прыжок если регистр равен 0
        memory[17]   = 32'b01000000000000000000000000000000;
        memory[18]   = 32'b10000100000000000000000000000100;   // прыжок если регистр равен 0


        memory[19]   = 32'b00000000000000000000000000000000;   // NOP
        memory[20]   = 32'b00000000000000000000000000000000;   // NOP
        memory[21]   = 32'b00000000000000000000000000000000;   // NOP


        // тут дальше заполняй память
        */
    end

    // чтение инструкции из памяти
    always @(*) 
    begin
        // достаточно 8 бит адреса, поскольку у нас всего 256 инструкций
        instruction = memory[address[7:0]]; 
        //i_result    = instruction[15:10];
        //i_a         = instruction[10:5];
        //i_b         = instruction[5:0];
    end

    

    

endmodule


module alu (
    input [31:0] a,             // первый операнд
    input [31:0] b,             // второй операнд
    input [5:0]  operation,     // код операции
    output reg [31:0] result,    // результат
    output reg [31:0] over // для остатока или переполнение

);

    always @(*) begin

        // по умолчанию устанавливаем результат в 0
        result = 32'b0;
        
        // выбираем операцию на основе входного кода операции
        case (operation)

            7'b000001: result = a + b;          // сложение
            7'b000010: result = a - b;          // вычитание
            7'b000011: result = a * b;          // умножение
            7'b000100: result = a / b;          // деление
            7'b000101: result = a & b;          // AND
            7'b000110: result = a | b;          // OR
            7'b000111: result = a ^ b;          // XOR
            7'b001000: result = ~(a | b);       // NOR
            7'b001001: result = a << b;         // сдвиг влево
            7'b001010: result = a >> b;         // арифметический сдвиг вправо
            7'b001011: result = a >>> b;        // логический сдвиг вправо

            //7'b010000: result = a ;             // запись в регистр
            // тут доп операции
        endcase
    end
    
endmodule

test_gownak.sv
`timescale 1ns/1ns
`include "gownak.sv"

module test_gownak;


reg clk;
reg [31:0]  PC;
reg [31:0]  instruction;

reg [4:0]   i_a;
reg [4:0]   i_b;
reg [5:0]   operation;
reg [4:0]   i_result;
reg [31:0]  over;


 
reg [31:0]  reg_0;
reg [31:0]  reg_1;
reg [31:0]  reg_2;
reg [31:0]  reg_3;
reg [31:0]  reg_4;
reg [31:0]  reg_5;



gownak uut(clk, PC, instruction,
            i_a, i_b, operation, i_result, over,
            
            reg_0,reg_1,reg_2,reg_3,reg_4,reg_5);

    initial begin
        
        $dumpfile("test_gownak.vcd");
        $dumpvars(0,test_gownak);
        clk = 0;




        #1000 $finish;
        $display("test done");

    end
    always #5 clk = ~clk;
    
endmodule

test_gownak.vcd
$date
	Thu Oct 12 19:00:05 2023
$end
$version
	Icarus Verilog
$end
$timescale
	1ns
$end
$scope module test_gownak $end
$var wire 32 ! reg_5 [31:0] $end
$var wire 32 " reg_4 [31:0] $end
$var wire 32 # reg_3 [31:0] $end
$var wire 32 $ reg_2 [31:0] $end
$var wire 32 % reg_1 [31:0] $end
$var wire 32 & reg_0 [31:0] $end
$var wire 32 ' over [31:0] $end
$var wire 6 ( operation [5:0] $end
$var wire 32 ) instruction [31:0] $end
$var wire 5 * i_result [4:0] $end
$var wire 5 + i_b [4:0] $end
$var wire 5 , i_a [4:0] $end
$var wire 32 - PC [31:0] $end
$var reg 1 . clk $end
$scope module uut $end
$var wire 1 . clk $end
$var wire 32 / reg_0 [31:0] $end
$var wire 32 0 reg_1 [31:0] $end
$var wire 32 1 reg_2 [31:0] $end
$var wire 32 2 reg_3 [31:0] $end
$var wire 32 3 reg_4 [31:0] $end
$var wire 32 4 reg_5 [31:0] $end
$var wire 6 5 operation [5:0] $end
$var wire 32 6 instruction [31:0] $end
$var wire 5 7 i_result [4:0] $end
$var wire 5 8 i_b [4:0] $end
$var wire 5 9 i_a [4:0] $end
$var reg 32 : FLAG [31:0] $end
$var reg 32 ; PC [31:0] $end
$var reg 32 < over [31:0] $end
$scope module instruction_memory_gate $end
$var wire 32 = address [31:0] $end
$var reg 32 > instruction [31:0] $end
$upscope $end
$scope begin $ivl_for_loop0 $end
$var integer 32 ? i [31:0] $end
$upscope $end
$upscope $end
$upscope $end
$enddefinitions $end
$comment Show the parameter values. $end
$dumpall
$end
#0
$dumpvars
b100000 ?
b0 >
b0 =
bx <
b0 ;
b0 :
b0 9
b0 8
b0 7
b0 6
b0 5
b0 4
b0 3
b0 2
b0 1
b0 0
b0 /
0.
b0 -
b0 ,
b0 +
b0 *
b0 )
b0 (
bx '
b0 &
b0 %
b0 $
b0 #
b0 "
b0 !
$end
#5
b10000 (
b10000 5
b11110 +
b11110 8
b1 *
b1 7
b1000000000000000000010000011110 )
b1000000000000000000010000011110 6
b1000000000000000000010000011110 >
b1 -
b1 ;
b1 =
1.
#10
b11110 %
b11110 0
0.
#15
b10010 +
b10010 8
b10 *
b10 7
b1000000000000000000100000010010 )
b1000000000000000000100000010010 6
b1000000000000000000100000010010 >
b10 -
b10 ;
b10 =
1.
#20
b10010 $
b10010 1
0.
#25
b0 (
b0 5
b0 +
b0 8
b0 *
b0 7
b0 )
b0 6
b0 >
b11 -
b11 ;
b11 =
1.
#30
0.
#35
b10 (
b10 5
b10 +
b10 8
b1 ,
b1 9
b1000000000000000000000100010 )
b1000000000000000000000100010 6
b1000000000000000000000100010 >
b100 -
b100 ;
b100 =
1.
#40
b1100 &
b1100 /
0.
#45
b100001 (
b100001 5
b0 +
b0 8
b100 ,
b100 9
b10000100000000000000000010000000 )
b10000100000000000000000010000000 6
b10000100000000000000000010000000 >
b101 -
b101 ;
b101 =
1.
#50
0.
#55
b100010 (
b100010 5
b10 +
b10 8
b1 ,
b1 9
b1001 *
b1001 7
b10001000000000000010010000100010 )
b10001000000000000010010000100010 6
b10001000000000000010010000100010 >
b110 -
b110 ;
b110 =
1.
#60
b100000 (
b100000 5
b11 +
b11 8
b0 ,
b0 9
b0 *
b0 7
b10000000000000000000000000000011 )
b10000000000000000000000000000011 6
b10000000000000000000000000000011 >
b1000 -
b1000 ;
b1000 =
0.
#65
b10 (
b10 5
b10 +
b10 8
b1 ,
b1 9
b1 *
b1 7
b1000000000000000010000100010 )
b1000000000000000010000100010 6
b1000000000000000010000100010 >
b1001 -
b1001 ;
b1001 =
1.
#70
b1100 %
b1100 0
0.
#75
b100000 (
b100000 5
b11 +
b11 8
b0 ,
b0 9
b0 *
b0 7
b10000000000000000000000000000011 )
b10000000000000000000000000000011 6
b10000000000000000000000000000011 >
b1010 -
b1010 ;
b1010 =
1.
#80
b10000 (
b10000 5
b10010 +
b10010 8
b10 *
b10 7
b1000000000000000000100000010010 )
b1000000000000000000100000010010 6
b1000000000000000000100000010010 >
b10 -
b10 ;
b10 =
0.
#85
b0 (
b0 5
b0 +
b0 8
b0 *
b0 7
b0 )
b0 6
b0 >
b11 -
b11 ;
b11 =
1.
#90
0.
#95
b10 (
b10 5
b10 +
b10 8
b1 ,
b1 9
b1000000000000000000000100010 )
b1000000000000000000000100010 6
b1000000000000000000000100010 >
b100 -
b100 ;
b100 =
1.
#100
b11111111111111111111111111111010 &
b11111111111111111111111111111010 /
0.
#105
b100001 (
b100001 5
b0 +
b0 8
b100 ,
b100 9
b10000100000000000000000010000000 )
b10000100000000000000000010000000 6
b10000100000000000000000010000000 >
b101 -
b101 ;
b101 =
1.
#110
0.
#115
b100010 (
b100010 5
b10 +
b10 8
b1 ,
b1 9
b1001 *
b1001 7
b10001000000000000010010000100010 )
b10001000000000000010010000100010 6
b10001000000000000010010000100010 >
b110 -
b110 ;
b110 =
1.
#120
0.
#125
b10 (
b10 5
b1 +
b1 8
b10 ,
b10 9
b10 *
b10 7
b1000000000000000100001000001 )
b1000000000000000100001000001 6
b1000000000000000100001000001 >
b111 -
b111 ;
b111 =
1.
#130
b110 $
b110 1
0.
#135
b100000 (
b100000 5
b11 +
b11 8
b0 ,
b0 9
b0 *
b0 7
b10000000000000000000000000000011 )
b10000000000000000000000000000011 6
b10000000000000000000000000000011 >
b1000 -
b1000 ;
b1000 =
1.
#140
b10000 (
b10000 5
b10010 +
b10010 8
b10 *
b10 7
b1000000000000000000100000010010 )
b1000000000000000000100000010010 6
b1000000000000000000100000010010 >
b10 -
b10 ;
b10 =
0.
#145
b0 (
b0 5
b0 +
b0 8
b0 *
b0 7
b0 )
b0 6
b0 >
b11 -
b11 ;
b11 =
1.
#150
0.
#155
b10 (
b10 5
b10 +
b10 8
b1 ,
b1 9
b1000000000000000000000100010 )
b1000000000000000000000100010 6
b1000000000000000000000100010 >
b100 -
b100 ;
b100 =
1.
#160
b110 &
b110 /
0.
#165
b100001 (
b100001 5
b0 +
b0 8
b100 ,
b100 9
b10000100000000000000000010000000 )
b10000100000000000000000010000000 6
b10000100000000000000000010000000 >
b101 -
b101 ;
b101 =
1.
#170
0.
#175
b100010 (
b100010 5
b10 +
b10 8
b1 ,
b1 9
b1001 *
b1001 7
b10001000000000000010010000100010 )
b10001000000000000010010000100010 6
b10001000000000000010010000100010 >
b110 -
b110 ;
b110 =
1.
#180
b100000 (
b100000 5
b11 +
b11 8
b0 ,
b0 9
b0 *
b0 7
b10000000000000000000000000000011 )
b10000000000000000000000000000011 6
b10000000000000000000000000000011 >
b1000 -
b1000 ;
b1000 =
0.
#185
b10 (
b10 5
b10 +
b10 8
b1 ,
b1 9
b1 *
b1 7
b1000000000000000010000100010 )
b1000000000000000010000100010 6
b1000000000000000010000100010 >
b1001 -
b1001 ;
b1001 =
1.
#190
b110 %
b110 0
0.
#195
b100000 (
b100000 5
b11 +
b11 8
b0 ,
b0 9
b0 *
b0 7
b10000000000000000000000000000011 )
b10000000000000000000000000000011 6
b10000000000000000000000000000011 >
b1010 -
b1010 ;
b1010 =
1.
#200
b10000 (
b10000 5
b10010 +
b10010 8
b10 *
b10 7
b1000000000000000000100000010010 )
b1000000000000000000100000010010 6
b1000000000000000000100000010010 >
b10 -
b10 ;
b10 =
0.
#205
b0 (
b0 5
b0 +
b0 8
b0 *
b0 7
b0 )
b0 6
b0 >
b11 -
b11 ;
b11 =
1.
#210
0.
#215
b10 (
b10 5
b10 +
b10 8
b1 ,
b1 9
b1000000000000000000000100010 )
b1000000000000000000000100010 6
b1000000000000000000000100010 >
b100 -
b100 ;
b100 =
1.
#220
b0 &
b0 /
0.
#225
b100001 (
b100001 5
b0 +
b0 8
b100 ,
b100 9
b10000100000000000000000010000000 )
b10000100000000000000000010000000 6
b10000100000000000000000010000000 >
b101 -
b101 ;
b101 =
1.
#230
bx (
bx 5
bx +
bx 8
bx ,
bx 9
bx *
bx 7
bx )
bx 6
bx >
b1111111 -
b1111111 ;
b1111111 =
0.
#235
b10000000 -
b10000000 ;
b10000000 =
1.
#240
0.
#245
b10000001 -
b10000001 ;
b10000001 =
1.
#250
0.
#255
b10000010 -
b10000010 ;
b10000010 =
1.
#260
0.
#265
b10000011 -
b10000011 ;
b10000011 =
1.
#270
0.
#275
b10000100 -
b10000100 ;
b10000100 =
1.
#280
0.
#285
b10000101 -
b10000101 ;
b10000101 =
1.
#290
0.
#295
b10000110 -
b10000110 ;
b10000110 =
1.
#300
0.
#305
b10000111 -
b10000111 ;
b10000111 =
1.
#310
0.
#315
b10001000 -
b10001000 ;
b10001000 =
1.
#320
0.
#325
b10001001 -
b10001001 ;
b10001001 =
1.
#330
0.
#335
b10001010 -
b10001010 ;
b10001010 =
1.
#340
0.
#345
b10001011 -
b10001011 ;
b10001011 =
1.
#350
0.
#355
b10001100 -
b10001100 ;
b10001100 =
1.
#360
0.
#365
b10001101 -
b10001101 ;
b10001101 =
1.
#370
0.
#375
b10001110 -
b10001110 ;
b10001110 =
1.
#380
0.
#385
b10001111 -
b10001111 ;
b10001111 =
1.
#390
0.
#395
b10010000 -
b10010000 ;
b10010000 =
1.
#400
0.
#405
b10010001 -
b10010001 ;
b10010001 =
1.
#410
0.
#415
b10010010 -
b10010010 ;
b10010010 =
1.
#420
0.
#425
b10010011 -
b10010011 ;
b10010011 =
1.
#430
0.
#435
b10010100 -
b10010100 ;
b10010100 =
1.
#440
0.
#445
b10010101 -
b10010101 ;
b10010101 =
1.
#450
0.
#455
b10010110 -
b10010110 ;
b10010110 =
1.
#460
0.
#465
b10010111 -
b10010111 ;
b10010111 =
1.
#470
0.
#475
b10011000 -
b10011000 ;
b10011000 =
1.
#480
0.
#485
b10011001 -
b10011001 ;
b10011001 =
1.
#490
0.
#495
b10011010 -
b10011010 ;
b10011010 =
1.
#500
0.
#505
b10011011 -
b10011011 ;
b10011011 =
1.
#510
0.
#515
b10011100 -
b10011100 ;
b10011100 =
1.
#520
0.
#525
b10011101 -
b10011101 ;
b10011101 =
1.
#530
0.
#535
b10011110 -
b10011110 ;
b10011110 =
1.
#540
0.
#545
b10011111 -
b10011111 ;
b10011111 =
1.
#550
0.
#555
b10100000 -
b10100000 ;
b10100000 =
1.
#560
0.
#565
b10100001 -
b10100001 ;
b10100001 =
1.
#570
0.
#575
b10100010 -
b10100010 ;
b10100010 =
1.
#580
0.
#585
b10100011 -
b10100011 ;
b10100011 =
1.
#590
0.
#595
b10100100 -
b10100100 ;
b10100100 =
1.
#600
0.
#605
b10100101 -
b10100101 ;
b10100101 =
1.
#610
0.
#615
b10100110 -
b10100110 ;
b10100110 =
1.
#620
0.
#625
b10100111 -
b10100111 ;
b10100111 =
1.
#630
0.
#635
b10101000 -
b10101000 ;
b10101000 =
1.
#640
0.
#645
b10101001 -
b10101001 ;
b10101001 =
1.
#650
0.
#655
b10101010 -
b10101010 ;
b10101010 =
1.
#660
0.
#665
b10101011 -
b10101011 ;
b10101011 =
1.
#670
0.
#675
b10101100 -
b10101100 ;
b10101100 =
1.
#680
0.
#685
b10101101 -
b10101101 ;
b10101101 =
1.
#690
0.
#695
b10101110 -
b10101110 ;
b10101110 =
1.
#700
0.
#705
b10101111 -
b10101111 ;
b10101111 =
1.
#710
0.
#715
b10110000 -
b10110000 ;
b10110000 =
1.
#720
0.
#725
b10110001 -
b10110001 ;
b10110001 =
1.
#730
0.
#735
b10110010 -
b10110010 ;
b10110010 =
1.
#740
0.
#745
b10110011 -
b10110011 ;
b10110011 =
1.
#750
0.
#755
b10110100 -
b10110100 ;
b10110100 =
1.
#760
0.
#765
b10110101 -
b10110101 ;
b10110101 =
1.
#770
0.
#775
b10110110 -
b10110110 ;
b10110110 =
1.
#780
0.
#785
b10110111 -
b10110111 ;
b10110111 =
1.
#790
0.
#795
b10111000 -
b10111000 ;
b10111000 =
1.
#800
0.
#805
b10111001 -
b10111001 ;
b10111001 =
1.
#810
0.
#815
b10111010 -
b10111010 ;
b10111010 =
1.
#820
0.
#825
b10111011 -
b10111011 ;
b10111011 =
1.
#830
0.
#835
b10111100 -
b10111100 ;
b10111100 =
1.
#840
0.
#845
b10111101 -
b10111101 ;
b10111101 =
1.
#850
0.
#855
b10111110 -
b10111110 ;
b10111110 =
1.
#860
0.
#865
b10111111 -
b10111111 ;
b10111111 =
1.
#870
0.
#875
b11000000 -
b11000000 ;
b11000000 =
1.
#880
0.
#885
b11000001 -
b11000001 ;
b11000001 =
1.
#890
0.
#895
b11000010 -
b11000010 ;
b11000010 =
1.
#900
0.
#905
b11000011 -
b11000011 ;
b11000011 =
1.
#910
0.
#915
b11000100 -
b11000100 ;
b11000100 =
1.
#920
0.
#925
b11000101 -
b11000101 ;
b11000101 =
1.
#930
0.
#935
b11000110 -
b11000110 ;
b11000110 =
1.
#940
0.
#945
b11000111 -
b11000111 ;
b11000111 =
1.
#950
0.
#955
b11001000 -
b11001000 ;
b11001000 =
1.
#960
0.
#965
b11001001 -
b11001001 ;
b11001001 =
1.
#970
0.
#975
b11001010 -
b11001010 ;
b11001010 =
1.
#980
0.
#985
b11001011 -
b11001011 ;
b11001011 =
1.
#990
0.
#995
b11001100 -
b11001100 ;
b11001100 =
1.
